<view xmlns="http://jmix.io/schema/flowui/view">
    <layout justifyContent="BETWEEN" classNames="horizontal-layout">
        <details summaryText="Default value change" opened="true" width="AUTO">
            <textField id="textField" placeholder="Start typing"/>
        </details>
        <details summaryText="Custom value change" opened="true" width="50%">
            <vbox padding="false">
                <textField id="valueChangeModeTextField" maxLength="140" helperText="0/140"/>
                <radioButtonGroup id="valueChangeModeRadioButtonGroup" label="ValueChangeMode"/>
            </vbox>
        </details>
    </layout>
</view>
